{
    "ingredients": {
        "Spaghetti": {
        "name": "Spaghetti",
        "weights": [
          200,
          0,
          0
        ],
        "time": 11,
        "ingredient_type": "Pasta",
        "matching_pasta": [],
        "matching_vegtables": [],
        "matching_cheese": [],
        "matching_meat": [],
        "matching_sauce": []
      },
      "Tagliatelle": {
        "name": "Tagliatelle",
        "weights": [
          200,
          0,
          0
        ],
        "time": 11,
        "ingredient_type": "Pasta",
        "matching_pasta": [],
        "matching_vegtables": [],
        "matching_cheese": [],
        "matching_meat": [],
        "matching_sauce": []
      },
      "Fettuccine": {
        "name": "Fettuccine",
        "weights": [
          200,
          0,
          0
        ],
        "time": 11,
        "ingredient_type": "Pasta",
        "matching_pasta": [],
        "matching_vegtables": [],
        "matching_cheese": [],
        "matching_meat": [],
        "matching_sauce": []
      },
      "Bolognese": {
        "name": "Bolognese",
        "weights": [
          400,
          0,
          0
        ],
        "time": 4,
        "ingredient_type": "Sauce",
        "matching_pasta": [],
        "matching_vegtables": ["Italian-vegetable-mix", "Peas", "CherryTomatoes"],
        "matching_cheese": ["Gouda", "Parmesan"],
        "matching_meat": ["Ground-beef", "Ham"],
        "matching_sauce": []
      },
      "Carbonara": {
        "name": "Carbonara",
        "weights": [
          400,
          0,
          0
        ],
        "time": 4,
        "ingredient_type": "Sauce",
        "matching_pasta": [],
        "matching_vegtables": ["Peas"],
        "matching_cheese": ["Parmesan"],
        "matching_meat": ["Ham"],
        "matching_sauce": []
      },
      "Gouda": {
        "name": "Gouda",
        "weights": [
          100,
          0,
          0
        ],
        "time": 0,
        "ingredient_type": "Cheese",
        "matching_pasta": [],
        "matching_vegtables": [],
        "matching_cheese": [],
        "matching_meat": [],
        "matching_sauce": []
      },
      "Parmesan": {
        "name": "Parmesan",
        "weights": [
          100,
          0,
          0
        ],
        "time": 0,
        "ingredient_type": "Cheese",
        "matching_pasta": [],
        "matching_vegtables": [],
        "matching_cheese": [],
        "matching_meat": [],
        "matching_sauce": []
      },
      "Ground-beef": {
        "name": "Ground-beef",
        "weights": [
          250,
          0,
          0
        ],
        "time": 4,
        "ingredient_type": "Meat",
        "matching_pasta": [],
        "matching_vegtables": [],
        "matching_cheese": [],
        "matching_meat": [],
        "matching_sauce": ["Bolognese"]
      },
      "Ham": {
        "name": "Ham",
        "weights": [
          300,
          0,
          0
        ],
        "time": 2,
        "ingredient_type": "Meat",
        "matching_pasta": [],
        "matching_vegtables": [],
        "matching_cheese": [],
        "matching_meat": [],
        "matching_sauce": ["Carbonara", "Bolognese"]
      },
      "Italian-vegetable-mix": {
        "name": "Italian-vegetable-mix",
        "weights": [
          400,
          0,
          0
        ],
        "time": 6,
        "ingredient_type": "Vegtable",
        "matching_pasta": ["Spaghetti"],
        "matching_vegtables": [],
        "matching_cheese": [],
        "matching_meat": [],
        "matching_sauce": []
      },
      "Peas": {
        "name": "Peas",
        "weights": [
          220,
          0,
          0
        ],
        "time": 6,
        "ingredient_type": "Vegtable",
        "matching_pasta": [],
        "matching_vegtables": [],
        "matching_cheese": [],
        "matching_meat": [],
        "matching_sauce": []
      },
      "CherryTomatoes": {
        "name": "Cherry tomatoes",
        "weights": [
          250,
          0,
          0
        ],
        "time": 5,
        "ingredient_type": "Vegtable",
        "matching_pasta": [],
        "matching_vegtables": [],
        "matching_cheese": [],
        "matching_meat": [],
        "matching_sauce": []
      },
      "Spinach": {
        "name": "Spinach",
        "weights": [
          0,
          0,
          0
        ],
        "time": 4,
        "ingredient_type": "Vegtable",
        "matching_pasta": [],
        "matching_vegtables": [],
        "matching_cheese": ["Gouda", "Gorgonzola", "Parmesan", "Ricotta"],
        "matching_meat": ["Bacon", "Anchovies", "Ground-beef"],
        "matching_sauce": ["Bolognese"]
      }
    }
  }